chibi_lxc/__init__.py
chibi_lxc/cli.py
chibi_lxc/config.py
chibi_lxc/container.py
chibi_lxc/snippets.py
chibi_lxc/file/__init__.py
chibi_lxc/file/config.py
chibi_lxc-1.0.0.dist-info/licenses/AUTHORS.rst
chibi_lxc-1.0.0.dist-info/licenses/LICENSE
chibi_lxc-1.0.0.dist-info/METADATA
chibi_lxc-1.0.0.dist-info/WHEEL
chibi_lxc-1.0.0.dist-info/entry_points.txt
chibi_lxc-1.0.0.dist-info/top_level.txt
chibi_lxc-1.0.0.dist-info/RECORD
