Metadata-Version: 2.4
Name: chibi_lxc
Version: 1.0.0
Summary: definition of lxc containers using python
Home-page: https://github.com/dem4ply/chibi_lxc
Author: dem4ply
Author-email: dem4ply@gmail.com
License: WTFPL
Keywords: chibi_lxc
Classifier: Development Status :: 2 - Pre-Alpha
Classifier: Intended Audience :: Developers
Classifier: License :: Public Domain
Classifier: Natural Language :: English
Classifier: Programming Language :: Python :: 3.7
Classifier: Programming Language :: Python :: 3.8
License-File: LICENSE
License-File: AUTHORS.rst
Requires-Dist: chibi>=0.8.2
Requires-Dist: chibi_donkey>=1.0.0
Requires-Dist: chibi-command>=0.2.3
Requires-Dist: python-hosts
Dynamic: author
Dynamic: author-email
Dynamic: classifier
Dynamic: description
Dynamic: home-page
Dynamic: keywords
Dynamic: license
Dynamic: license-file
Dynamic: requires-dist
Dynamic: summary
